sre_tools/__init__.py
sre_tools/_simplify.py
sre_tools/_split.py
sre_tools/simplify.py
sre_tools/utils.py
sre_tools-0.0.1.dist-info/LICENSE
sre_tools-0.0.1.dist-info/METADATA
sre_tools-0.0.1.dist-info/WHEEL
sre_tools-0.0.1.dist-info/top_level.txt
sre_tools-0.0.1.dist-info/version.txt
sre_tools-0.0.1.dist-info/RECORD
